ab_client/token_validator/__init__.py
ab_client/token_validator/clients/__init__.py
ab_client/token_validator/clients/async_client.py
ab_client/token_validator/clients/sync_client.py
ab_client/token_validator/exceptions/__init__.py
ab_client/token_validator/exceptions/http_exception.py
ab_client/token_validator/models/HTTPValidationError.py
ab_client/token_validator/models/ValidateTokenRequest.py
ab_client/token_validator/models/ValidatedOIDCClaims.py
ab_client/token_validator/models/ValidationError.py
ab_client/token_validator/models/__init__.py
ab_client_token_validator-1.1.1.dist-info/METADATA
ab_client_token_validator-1.1.1.dist-info/WHEEL
ab_client_token_validator-1.1.1.dist-info/licenses/LICENSE
ab_client_token_validator-1.1.1.dist-info/RECORD
